modal_run/__init__.py
modal_run/cli.py
modal_run-0.1.3.dist-info/licenses/LICENSE
modal_run-0.1.3.dist-info/METADATA
modal_run-0.1.3.dist-info/WHEEL
modal_run-0.1.3.dist-info/entry_points.txt
modal_run-0.1.3.dist-info/top_level.txt
modal_run-0.1.3.dist-info/RECORD
