Metadata-Version: 2.4
Name: modal-run
Version: 0.1.3
Summary: Simple CLI tool to run deployed Modal functions
Author: Nikita Demir
License: MIT
Project-URL: Homepage, https://github.com/N-Demir/modal-run
Requires-Python: >=3.8
License-File: LICENSE
Requires-Dist: typer>=0.9.0
Requires-Dist: click>=8.1.0
Requires-Dist: modal>=0.0.1
Dynamic: license-file
